{
    "urn:jsonschema:com:java:domain:Access": "/api/access/",
    "urn:jsonschema:com:java:domain:CanTeach": "/api/canteach/",
    "urn:jsonschema:com:java:domain:Classroom": "/api/classroom/",
    "urn:jsonschema:com:java:domain:ClassroomType": "/api/classroomtype/",
    "urn:jsonschema:com:java:domain:Corps": "/api/corps/",
    "urn:jsonschema:com:java:domain:Course": "/api/course/",
    "urn:jsonschema:com:java:domain:Deanery": "/api/deanery/",
    "urn:jsonschema:com:java:domain:EducationForm": "/api/educationform/",
    "urn:jsonschema:com:java:domain:Faculty": "/api/faculty/",
    "urn:jsonschema:com:java:domain:Flow": "/api/flow/",
    "urn:jsonschema:com:java:domain:Groups": "/api/groups/",
    "urn:jsonschema:com:java:domain:LearningSeverity": "/api/learningseverity/",
    "urn:jsonschema:com:java:domain:LearningSeverityList": "/api/learningseveritylist/",
    "urn:jsonschema:com:java:domain:Lectern": "/api/lectern/",
    "urn:jsonschema:com:java:domain:LecternType": "/api/lecterntype/",
    "urn:jsonschema:com:java:domain:Lesson": "/api/lesson/",
    "urn:jsonschema:com:java:domain:NeededLesson": "/api/neededlesson/",
    "urn:jsonschema:com:java:domain:Occupation": "/api/occupation/",
    "urn:jsonschema:com:java:domain:OccupationCounter": "/api/occupationcounter/",
    "urn:jsonschema:com:java:domain:OccupationCounterCourse": "/api/OccupationCounterCourse/",
    "urn:jsonschema:com:java:domain:PereodicSeverity": "/api/pereodicseverity/",
    "urn:jsonschema:com:java:domain:PereodicSeveritySubject": "/api/pereodicseveritysubject/",
    "urn:jsonschema:com:java:domain:Role": "/api/role/",
    "urn:jsonschema:com:java:domain:Schedule": "/api/schedule/",
    "urn:jsonschema:com:java:domain:Semester": "/api/semester/",
    "urn:jsonschema:com:java:domain:SemesterNumber": "/api/semesternumber/",
    "urn:jsonschema:com:java:domain:Severity": "/api/severity/",
    "urn:jsonschema:com:java:domain:SeveritySubject": "/api/severitysubject/",
    "urn:jsonschema:com:java:domain:Speciality": "/api/speciality/",
    "urn:jsonschema:com:java:domain:StudyPlan": "/api/studyplan/",
    "urn:jsonschema:com:java:domain:StudyPlanStatus": "/api/studyplanstatus/",
    "urn:jsonschema:com:java:domain:Subgroup": "/api/subgroup/",
    "urn:jsonschema:com:java:domain:Subject": "/api/subject/",
    "urn:jsonschema:com:java:domain:Syllabus": "/api/syllabus/",
    "urn:jsonschema:com:java:domain:Teacher": "/api/teacher/",
    "urn:jsonschema:com:java:domain:Turn": "/api/turn/",
    "urn:jsonschema:com:java:domain:TypeOfLesson": "/api/typeoflesson/",
    "urn:jsonschema:com:java:domain:UserRoles": "/api/userroles/",
    "urn:jsonschema:com:java:domain:Users": "/users/",
    "urn:jsonschema:com:java:domain:Week": "/api/week/",
    "urn:jsonschema:com:java:domain:Employee": "/api/employee/",
    "urn:jsonschema:com:java:domain:WeekCount": "/api/weekcount/"
}